{
  "required": true,
  "package": "com.zhilizhan.bhtpvz.common.mixin",
  "compatibilityLevel": "JAVA_17",
  "refmap": "bhtpvz.refmap.json",
  "mixins": [
    "LevelMixin",
    "PeaGunItemMixin",
    "PlantCardItemMixin",
    "PlayerEventHandlerMixin",
    "PVZPlantEntityMixin",
    "TorchWoodEntityMixin",
    "optional.PuffshroomEntityMixin",
    "optional.ScaredyShroomEntityMixin"
  ],
  "server": [
  ],
  "client": [
    "ClientProxyMixin",
    "LivingEntityRenderMixin",
    "PVZPlantRenderMixin",
    "optional.PuffShroomRenderMixin"
  ],
  "minVersion": "0.8.0"
}
